gigui/__init__.py
gigui/__main__.py
gigui/_logging.py
gigui/args_settings.py
gigui/cli.py
gigui/cli_arguments.py
gigui/comment.py
gigui/constants.py
gigui/data.py
gigui/gi_runner.py
gigui/gi_runner_base.py
gigui/keys.py
gigui/messages.py
gigui/person_data.py
gigui/repo_base.py
gigui/repo_blame.py
gigui/repo_data.py
gigui/repo_runner.py
gigui/runner_queues.py
gigui/shared.py
gigui/tiphelp.py
gigui/typedefs.py
gigui/utils.py
gigui/version.txt
gigui/gui/psg.py
gigui/gui/psg_base.py
gigui/gui/psg_window.py
gigui/gui/psg_window_support.py
gigui/gui/images/icon.icns
gigui/gui/images/icon.ico
gigui/gui/images/icon.png
gigui/output/excel_sheet.py
gigui/output/repo_blame_rows.py
gigui/output/repo_excel.py
gigui/output/repo_html.py
gigui/output/repo_html_server.py
gigui/output/repo_stat_rows.py
gigui/output/static/styles.css
gigui/output/static/template.html
gigui/output/static/js/browser-id.js
gigui/output/static/js/globals.js
gigui/output/static/js/shutdown.js
gigui/output/static/js/tab-radio-button-activation.js
gigui/output/static/js/truncate-tab-names.js
gigui/output/static/js/update-table-on-button-click.js
gitinspectorgui-0.4.5.dist-info/METADATA
gitinspectorgui-0.4.5.dist-info/WHEEL
gitinspectorgui-0.4.5.dist-info/entry_points.txt
gitinspectorgui-0.4.5.dist-info/RECORD
