Metadata-Version: 2.4
Name: gitinspectorgui
Version: 0.4.5
Summary: A CLI and GUI tool for numerical and blame analysis of git repositories.
Project-URL: homepage, https://gitinspectorgui.readthedocs.io/en/latest/index.html
Project-URL: repository, https://github.com/davbeek/gitinspectorgui
Author-email: Bert van Beek <d.a.v.beek@tue.nl>
License: MIT
Keywords: analysis,analyzer,blame,cli,git,gui,repositories,repository,statistics
Classifier: Development Status :: 4 - Beta
Classifier: License :: OSI Approved :: MIT License
Classifier: Natural Language :: English
Classifier: Operating System :: MacOS
Classifier: Operating System :: Microsoft :: Windows :: Windows 10
Classifier: Operating System :: Microsoft :: Windows :: Windows 11
Classifier: Operating System :: POSIX :: Linux
Classifier: Programming Language :: Python :: 3.12
Requires-Python: <3.13,>=3.12
Requires-Dist: beautifulsoup4>=4.12.3
Requires-Dist: charset-normalizer==3.4.1
Requires-Dist: colorlog>=6.9
Requires-Dist: dmgbuild>=1.6.4
Requires-Dist: gitpython>=3.1.43
Requires-Dist: jinja2>=3.1.4
Requires-Dist: jsonschema>=4.23
Requires-Dist: platformdirs>=4.3.6
Requires-Dist: pysimplegui-4-foss==4.60.4.1
Requires-Dist: requests==2.32.3
Requires-Dist: ruff>=0.9.7
Requires-Dist: types-beautifulsoup4>=4.12
Requires-Dist: types-jsonschema>=4.23
Requires-Dist: types-requests==2.32.0.20241016
Requires-Dist: urllib3==2.3.0
Requires-Dist: werkzeug>=3.1.3
Requires-Dist: xlsxwriter>=3.2
